AUTHORS.rst
CONTRIBUTING.rst
HISTORY.rst
LICENSE
MANIFEST.in
README.rst
requirements.txt
setup.cfg
setup.py
docs/Makefile
docs/authors.rst
docs/conf.py
docs/contributing.rst
docs/history.rst
docs/index.rst
docs/installation.rst
docs/make.bat
docs/passwords.rst
docs/readme.rst
docs/usage.rst
passwordmetrics/__init__.py
passwordmetrics/wordlist_en.txt
passwordmetrics.egg-info/PKG-INFO
passwordmetrics.egg-info/SOURCES.txt
passwordmetrics.egg-info/dependency_links.txt
passwordmetrics.egg-info/not-zip-safe
passwordmetrics.egg-info/top_level.txt
tests/__init__.py
tests/test_docs.py
tests/test_passwordmetrics.py
utils/ANC-written-count.txt
utils/wordlist_compile.py