Metadata-Version: 1.1
Name: passwordmetrics
Version: 1.0
Summary: Checking the entropy of a password. Useful in password checkers.
Home-page: https://github.com/regebro/passwordmetrics
Author: Lennart Regebro
Author-email: regebro@gmail.com
License: MIT
Keywords: passwordmetrics
Platform: UNKNOWN
Classifier: Development Status :: 5 - Production/Stable
Classifier: Intended Audience :: Developers
Classifier: License :: OSI Approved :: MIT License
Classifier: Natural Language :: English
Classifier: Programming Language :: Python :: 2
Classifier: Programming Language :: Python :: 2.7
Classifier: Programming Language :: Python :: 3
Classifier: Programming Language :: Python :: 3.3
Classifier: Programming Language :: Python :: 3.4
Classifier: Programming Language :: Python :: 3.5
Classifier: Programming Language :: Python :: 3.6
Classifier: Programming Language :: Python :: Implementation :: PyPy
